xconnectpy/__init__.py
xconnectpy/xconnect_client.py
xconnectpy/lib/__init__.py
xconnectpy/lib/base/__init__.py
xconnectpy/lib/base/client.py
xconnectpy/lib/base/entity.py
xconnectpy/lib/base/facet.py
xconnectpy/lib/base/request.py
xconnectpy/lib/sitecore/__init__.py
xconnectpy/lib/sitecore/address.py
xconnectpy/lib/sitecore/address_list.py
xconnectpy/lib/sitecore/contact.py
xconnectpy/lib/sitecore/contact_identifier.py
xconnectpy/lib/sitecore/contact_identifier_type.py
xconnectpy/lib/sitecore/device_profile.py
xconnectpy/lib/sitecore/email_address.py
xconnectpy/lib/sitecore/email_address_list.py
xconnectpy/lib/sitecore/entity_reference.py
xconnectpy/lib/sitecore/expand_options.py
xconnectpy/lib/sitecore/facet_reference.py
xconnectpy/lib/sitecore/identified_contact_reference.py
xconnectpy/lib/sitecore/interaction.py
xconnectpy/lib/sitecore/interaction_initiator.py
xconnectpy/lib/sitecore/outcome.py
xconnectpy/lib/sitecore/personal_information.py
xconnectpy/lib/util/__init__.py
xconnectpy/lib/util/config_parser.py
xconnectpy/lib/util/guid.py
xconnectpy/lib/util/logger.py
xconnectpy/lib/util/odata.py
xconnectpy/lib/util/ssl.py
xconnectpy-0.0.1.dist-info/DESCRIPTION.rst
xconnectpy-0.0.1.dist-info/METADATA
xconnectpy-0.0.1.dist-info/RECORD
xconnectpy-0.0.1.dist-info/WHEEL
xconnectpy-0.0.1.dist-info/metadata.json
xconnectpy-0.0.1.dist-info/top_level.txt
