Metadata-Version: 2.0
Name: xconnectpy
Version: 0.0.1
Summary: Python library for interfacing Sitecore xConnect.
Home-page: http://www.coria.com
Author: Josip Ivković
Author-email: jivkovic@coria.com
License: Apache2
Platform: UNKNOWN
Requires-Python: ~=3.5
Requires-Dist: overloading
